{
  "project_info": {
    "project_number": "256318830208",
    "project_id": "cse-academic-92d65",
    "storage_bucket": "cse-academic-92d65.appspot.com"
  },
  "client": [
    {
      "client_info": {
        "mobilesdk_app_id": "1:256318830208:android:3957d6c1c86d1dae58d865",
        "android_client_info": {
          "package_name": "com.ashfaq.cse_academic"
        }
      },
      "oauth_client": [
        {
          "client_id": "256318830208-nu2nm12q4oatq3fl4m2ddff93ahs0hok.apps.googleusercontent.com",
          "client_type": 3
        }
      ],
      "api_key": [
        {
          "current_key": "AIzaSyBNuYsCd1ZoOip869mCXZa-E4ou91c6e3I"
        }
      ],
      "services": {
        "appinvite_service": {
          "other_platform_oauth_client": [
            {
              "client_id": "256318830208-nu2nm12q4oatq3fl4m2ddff93ahs0hok.apps.googleusercontent.com",
              "client_type": 3
            }
          ]
        }
      }
    }
  ],
  "configuration_version": "1"
}